dearpygui_ext/__init__.py
dearpygui_ext/logger.py
dearpygui_ext/themes.py
dearpygui_ext/utilities.py
dearpygui_ext-2.0.0.dist-info/LICENSE
dearpygui_ext-2.0.0.dist-info/METADATA
dearpygui_ext-2.0.0.dist-info/WHEEL
dearpygui_ext-2.0.0.dist-info/top_level.txt
dearpygui_ext-2.0.0.dist-info/RECORD
